crimson/intelli_type/__init__.py
crimson/intelli_type/_util.py
crimson/intelli_type/intelliType.py
crimson_intelli_type-0.4.0.dist-info/LICENSE
crimson_intelli_type-0.4.0.dist-info/METADATA
crimson_intelli_type-0.4.0.dist-info/WHEEL
crimson_intelli_type-0.4.0.dist-info/top_level.txt
crimson_intelli_type-0.4.0.dist-info/RECORD
