Metadata-Version: 2.1
Name: crimson-intelli-type
Version: 0.4.0
Summary: Typehints with documentation.
Author-email: Sisung Kim <sisung.kim1@gmail.com>
Project-URL: Homepage, https://github.com/crimson206/intelli-type
Project-URL: Bug Tracker, https://github.com/crimson206/intelli-type/issues
Classifier: Programming Language :: Python :: 3
Classifier: Intended Audience :: Developers
Classifier: Topic :: Software Development :: Build Tools
Classifier: License :: OSI Approved :: MIT License
Classifier: Operating System :: OS Independent
Requires-Python: >=3.9
License-File: LICENSE
Requires-Dist: pydantic
